PythonJiqirenXuexiShouceChuyiFix1/README.md
PythonJiqirenXuexiShouceChuyiFix1/__init__.py
PythonJiqirenXuexiShouceChuyiFix1/__main__.py
PythonJiqirenXuexiShouceChuyiFix1/file.epub
PythonJiqirenXuexiShouceChuyiFix1/index.html
PythonJiqirenXuexiShouceChuyiFix1/css/__init__.py
PythonJiqirenXuexiShouceChuyiFix1/css/annotations.css
PythonJiqirenXuexiShouceChuyiFix1/css/main.css
PythonJiqirenXuexiShouceChuyiFix1/css/normalize.css
PythonJiqirenXuexiShouceChuyiFix1/css/popup.css
PythonJiqirenXuexiShouceChuyiFix1/font/__init__.py
PythonJiqirenXuexiShouceChuyiFix1/font/fontello.eot
PythonJiqirenXuexiShouceChuyiFix1/font/fontello.svg
PythonJiqirenXuexiShouceChuyiFix1/font/fontello.ttf
PythonJiqirenXuexiShouceChuyiFix1/font/fontello.woff
PythonJiqirenXuexiShouceChuyiFix1/img/__init__.py
PythonJiqirenXuexiShouceChuyiFix1/img/annotator-glyph-sprite.png
PythonJiqirenXuexiShouceChuyiFix1/img/annotator-icon-sprite.png
PythonJiqirenXuexiShouceChuyiFix1/img/apple-touch-icon.png
PythonJiqirenXuexiShouceChuyiFix1/img/cancelfullscreen.png
PythonJiqirenXuexiShouceChuyiFix1/img/close.png
PythonJiqirenXuexiShouceChuyiFix1/img/fullscreen.png
PythonJiqirenXuexiShouceChuyiFix1/img/loader.gif
PythonJiqirenXuexiShouceChuyiFix1/img/menu-icon.png
PythonJiqirenXuexiShouceChuyiFix1/img/save.png
PythonJiqirenXuexiShouceChuyiFix1/img/saved.png
PythonJiqirenXuexiShouceChuyiFix1/img/settings-s.png
PythonJiqirenXuexiShouceChuyiFix1/img/settings.png
PythonJiqirenXuexiShouceChuyiFix1/img/star.png
PythonJiqirenXuexiShouceChuyiFix1/js/__init__.py
PythonJiqirenXuexiShouceChuyiFix1/js/epub.js
PythonJiqirenXuexiShouceChuyiFix1/js/epub.min.js
PythonJiqirenXuexiShouceChuyiFix1/js/epub.min.map
PythonJiqirenXuexiShouceChuyiFix1/js/hooks.min.js
PythonJiqirenXuexiShouceChuyiFix1/js/hooks.min.map
PythonJiqirenXuexiShouceChuyiFix1/js/reader.js
PythonJiqirenXuexiShouceChuyiFix1/js/reader.js.map
PythonJiqirenXuexiShouceChuyiFix1/js/reader.min.js
PythonJiqirenXuexiShouceChuyiFix1/js/reader.min.map
python_jiqiren_xuexi_shouce_chuyi_fix1-2025.3.25.1.dist-info/METADATA
python_jiqiren_xuexi_shouce_chuyi_fix1-2025.3.25.1.dist-info/WHEEL
python_jiqiren_xuexi_shouce_chuyi_fix1-2025.3.25.1.dist-info/entry_points.txt
python_jiqiren_xuexi_shouce_chuyi_fix1-2025.3.25.1.dist-info/top_level.txt
python_jiqiren_xuexi_shouce_chuyi_fix1-2025.3.25.1.dist-info/RECORD
